ansicat.py
cert_migration.py
netcache.py
netcache_migration.py
offblocklist.py
offpunk.py
offthemes.py
offutils.py
opnk.py
offpunk-2.6.dist-info/METADATA
offpunk-2.6.dist-info/WHEEL
offpunk-2.6.dist-info/entry_points.txt
offpunk-2.6.dist-info/licenses/LICENSE
offpunk-2.6.dist-info/RECORD
