Metadata-Version: 2.4
Name: offpunk
Version: 2.6
Dynamic: Summary
Project-URL: Homepage, https://offpunk.net/
Project-URL: Source, https://git.sr.ht/~lioploum/offpunk
Project-URL: Bug Tracker, https://todo.sr.ht/~lioploum/offpunk
Author-email: Solderpunk <solderpunk@sdf.org>, "Lionel Dricot (Ploum)" <offpunk2@ploum.eu>
Maintainer-email: "Lionel Dricot (Ploum)" <offpunk2@ploum.eu>
License:                     GNU AFFERO GENERAL PUBLIC LICENSE
License-File: LICENSE
Keywords: browser,gemini
Classifier: Development Status :: 4 - Beta
Classifier: Environment :: Console
Classifier: License :: OSI Approved :: GNU Affero General Public License v3 or later (AGPLv3+)
Classifier: Operating System :: OS Independent
Classifier: Programming Language :: Python :: 3 :: Only
Classifier: Topic :: Communications
Classifier: Topic :: Internet
Requires-Python: >=3.7
Provides-Extra: better-tofu
Requires-Dist: cryptography; extra == 'better-tofu'
Provides-Extra: chardet
Requires-Dist: chardet; extra == 'chardet'
Provides-Extra: html
Requires-Dist: bs4; extra == 'html'
Requires-Dist: readability-lxml; extra == 'html'
Provides-Extra: http
Requires-Dist: requests; extra == 'http'
Provides-Extra: process-title
Requires-Dist: setproctitle; extra == 'process-title'
Provides-Extra: rss
Requires-Dist: feedparser; extra == 'rss'
